otter/__init__.py
otter/client.py
otter/constants.py
otter/core.py
otter/decorators.py
otter/singleton.py
otter/utils.py
otterpy-1.0.dist-info/LICENSE
otterpy-1.0.dist-info/METADATA
otterpy-1.0.dist-info/WHEEL
otterpy-1.0.dist-info/top_level.txt
otterpy-1.0.dist-info/RECORD
