Metadata-Version: 2.1
Name: otterpy
Version: 1.0
Summary: Otter - framework for microservices.
Home-page: https://github.com/volbil/otter
Author: Volodymyr Biloshytskyi
Author-email: volbil@protonmail.com
License: MIT
Platform: UNKNOWN
Classifier: Programming Language :: Python :: 3
Classifier: License :: OSI Approved :: MIT License
Classifier: Operating System :: OS Independent
License-File: LICENSE
Requires-Dist: aio-pika (==6.8.0)
Requires-Dist: aiormq (==3.3.1)
Requires-Dist: async-generator (==1.10)
Requires-Dist: deprecation (==2.1.0)
Requires-Dist: idna (==3.2)
Requires-Dist: kiwipy (==0.7.4)
Requires-Dist: marshmallow (==3.13.0)
Requires-Dist: multidict (==5.1.0)
Requires-Dist: packaging (==21.0)
Requires-Dist: pamqp (==2.3.0)
Requires-Dist: pyparsing (==2.4.7)
Requires-Dist: pytray (==0.3.2)
Requires-Dist: PyYAML (==5.4.1)
Requires-Dist: shortuuid (==1.0.1)
Requires-Dist: yarl (==1.6.3)
